remixtree_cli/__init__.py
remixtree_cli/main.py
remixtree_cli/node.py
remixtree_cli-0.1.3.dist-info/licenses/LICENSE
remixtree_cli-0.1.3.dist-info/METADATA
remixtree_cli-0.1.3.dist-info/WHEEL
remixtree_cli-0.1.3.dist-info/entry_points.txt
remixtree_cli-0.1.3.dist-info/top_level.txt
remixtree_cli-0.1.3.dist-info/RECORD
