Metadata-Version: 2.4
Name: remixtree-cli
Version: 0.1.3
Summary: remake scratch's remix tree feature #BringBackRemixTrees
License: MIT
Project-URL: Homepage, https://github.com/Alastrantia/scratch-remixtree
Project-URL: BugTracker, https://github.com/Alastrantia/scratch-remixtree/issues
Requires-Python: >=3.9
License-File: LICENSE
Requires-Dist: aiohttp
Requires-Dist: rich
Dynamic: license-file
